reformer_pytorch/__init__.py
reformer_pytorch/autopadder.py
reformer_pytorch/generative_tools.py
reformer_pytorch/recorder.py
reformer_pytorch/reformer_enc_dec.py
reformer_pytorch/reformer_pytorch.py
reformer_pytorch/reversible.py
reformer_pytorch-1.4.4.dist-info/LICENSE
reformer_pytorch-1.4.4.dist-info/METADATA
reformer_pytorch-1.4.4.dist-info/WHEEL
reformer_pytorch-1.4.4.dist-info/top_level.txt
reformer_pytorch-1.4.4.dist-info/RECORD
