Metadata-Version: 2.1
Name: reformer-pytorch
Version: 1.4.4
Summary: Reformer, the Efficient Transformer, Pytorch
Home-page: https://github.com/lucidrains/reformer-pytorch
Author: Phil Wang
Author-email: lucidrains@gmail.com
License: MIT
Keywords: transformers,attention,artificial intelligence
Platform: UNKNOWN
Classifier: Development Status :: 4 - Beta
Classifier: Intended Audience :: Developers
Classifier: Topic :: Scientific/Engineering :: Artificial Intelligence
Classifier: License :: OSI Approved :: MIT License
Classifier: Programming Language :: Python :: 3.6
License-File: LICENSE
Requires-Dist: axial-positional-embedding (>=0.1.0)
Requires-Dist: einops
Requires-Dist: local-attention
Requires-Dist: product-key-memory
Requires-Dist: torch
